CHANGES.rst
LICENSE
MANIFEST.in
README.rst
VERSION
requirements.txt
setup.cfg
setup.py
springboard/__init__.py
springboard/__init__.pyc
springboard/application.py
springboard/application.pyc
springboard/auth.py
springboard/auth.pyc
springboard/config.py
springboard/config.pyc
springboard/defaults.ini
springboard/events.py
springboard/events.pyc
springboard/filters.py
springboard/filters.pyc
springboard/tasks.py
springboard/tasks.pyc
springboard/utils.py
springboard/utils.pyc
springboard.egg-info/PKG-INFO
springboard.egg-info/SOURCES.txt
springboard.egg-info/dependency_links.txt
springboard.egg-info/entry_points.txt
springboard.egg-info/not-zip-safe
springboard.egg-info/requires.txt
springboard.egg-info/top_level.txt
springboard/locale/README.rst
springboard/static/css/README
springboard/static/css/style.css
springboard/static/img/000000.png
springboard/static/img/README
springboard/static/img/logo000000.png
springboard/templates/404.jinja2
springboard/templates/atoms.html
springboard/templates/auth.jinja2
springboard/templates/base.jinja2
springboard/templates/category.jinja2
springboard/templates/flat_page.jinja2
springboard/templates/home.jinja2
springboard/templates/locale_change.jinja2
springboard/templates/molecules.html
springboard/templates/organisms.html
springboard/templates/page.jinja2
springboard/templates/search_results.jinja2
springboard/tests/__init__.py
springboard/tests/__init__.pyc
springboard/tests/base.py
springboard/tests/base.pyc
springboard/tests/test_auth.py
springboard/tests/test_events.py
springboard/tests/test_filters.py
springboard/tests/test_language.py
springboard/tests/test_search.py
springboard/tests/test_springboard.yaml
springboard/tests/test_tasks.py
springboard/tests/test_tools.py
springboard/tests/test_utils.py
springboard/tests/test_views.py
springboard/tests/__pycache__/test_auth.cpython-27-PYTEST.pyc
springboard/tests/__pycache__/test_events.cpython-27-PYTEST.pyc
springboard/tests/__pycache__/test_filters.cpython-27-PYTEST.pyc
springboard/tests/__pycache__/test_language.cpython-27-PYTEST.pyc
springboard/tests/__pycache__/test_search.cpython-27-PYTEST.pyc
springboard/tests/__pycache__/test_tasks.cpython-27-PYTEST.pyc
