Metadata-Version: 1.1
Name: springboard
Version: 3.1.0
Summary: Springboard
Home-page: http://github.com/smn/springboard
Author: Praekelt Foundation
Author-email: dev@praekelt.com
License: BSD
Keywords: web
Platform: UNKNOWN
Classifier: Programming Language :: Python
Classifier: Topic :: Internet :: WWW/HTTP
Classifier: Topic :: Internet :: WWW/HTTP :: WSGI :: Application
